odoo8_addon_base_import_match-8.0.1.0.1-py2.7-nspkg.pth
odoo8_addon_base_import_match-8.0.1.0.1.dist-info/top_level.txt
odoo8_addon_base_import_match-8.0.1.0.1.dist-info/WHEEL
odoo8_addon_base_import_match-8.0.1.0.1.dist-info/RECORD
odoo8_addon_base_import_match-8.0.1.0.1.dist-info/metadata.json
odoo8_addon_base_import_match-8.0.1.0.1.dist-info/DESCRIPTION.rst
odoo8_addon_base_import_match-8.0.1.0.1.dist-info/METADATA
odoo8_addon_base_import_match-8.0.1.0.1.dist-info/namespace_packages.txt
odoo_addons/base_import_match/__openerp__.py
odoo_addons/base_import_match/__init__.py
odoo_addons/base_import_match/README.rst
odoo_addons/base_import_match/security/ir.model.access.csv
odoo_addons/base_import_match/models/base_import.py
odoo_addons/base_import_match/models/__init__.py
odoo_addons/base_import_match/i18n/zh_CN.po
odoo_addons/base_import_match/i18n/ru.po
odoo_addons/base_import_match/i18n/pt.po
odoo_addons/base_import_match/i18n/it.po
odoo_addons/base_import_match/i18n/es.po
odoo_addons/base_import_match/i18n/tr.po
odoo_addons/base_import_match/i18n/fr_CA.po
odoo_addons/base_import_match/i18n/gl.po
odoo_addons/base_import_match/i18n/ca.po
odoo_addons/base_import_match/i18n/sl.po
odoo_addons/base_import_match/i18n/es_ES.po
odoo_addons/base_import_match/i18n/pt_PT.po
odoo_addons/base_import_match/i18n/nl.po
odoo_addons/base_import_match/i18n/am.po
odoo_addons/base_import_match/i18n/de.po
odoo_addons/base_import_match/i18n/fr.po
odoo_addons/base_import_match/i18n/pt_BR.po
odoo_addons/base_import_match/i18n/el_GR.po
odoo_addons/base_import_match/i18n/fi.po
odoo_addons/base_import_match/views/base_import_match_view.xml
odoo_addons/base_import_match/data/base_import_match.yml
odoo_addons/base_import_match/tests/test_import.py
odoo_addons/base_import_match/tests/__init__.py
odoo_addons/base_import_match/tests/import_data/res_partner_parent_name_is_company.csv
odoo_addons/base_import_match/tests/import_data/res_partner_email.csv
odoo_addons/base_import_match/tests/import_data/res_partner_name.csv
odoo_addons/base_import_match/tests/import_data/res_partner_vat.csv
odoo_addons/base_import_match/tests/import_data/res_users_login.csv
odoo_addons/base_import_match/demo/base_import_match.yml
odoo_addons/base_import_match/static/description/icon.png
